book_management_system/__init__.py
book_management_system/__main__.py
book_management_system_001-0.1.1.dist-info/METADATA
book_management_system_001-0.1.1.dist-info/WHEEL
book_management_system_001-0.1.1.dist-info/top_level.txt
book_management_system_001-0.1.1.dist-info/RECORD
