Metadata-Version: 2.4
Name: book_management_system_001
Version: 0.1.1
Summary: A short description
Author-email: srinithi <srinithimcse@gmail.com>
License: MIT
Project-URL: Homepage, https://github.com/srinithi2546/your-repo
Classifier: Programming Language :: Python :: 3
Classifier: License :: OSI Approved :: MIT License
Requires-Python: >=3.7
